circuitgym/__init__.py
circuitgym/envs.py
circuitgym/experience.py
circuitgym/parallel.py
circuitgym/spaces.py
circuitgym-0.1b4.dist-info/METADATA
circuitgym-0.1b4.dist-info/RECORD
circuitgym-0.1b4.dist-info/WHEEL
circuitgym-0.1b4.dist-info/top_level.txt
