Metadata-Version: 2.1
Name: circuitgym
Version: 0.1b4
Summary: OpenAI-gym -like environments for spice circuits
Home-page: https://github.gatech.edu/lars/circuitgym
Author: Barry Muldrey
Author-email: bmuldrey3@gatech.edu
License: UNKNOWN
Platform: UNKNOWN
Requires-Dist: gym
Requires-Dist: pyspectre (>=0.1b10)
Requires-Dist: pandas
Requires-Dist: numpy
